cubicweb_timesheet/__init__.py
cubicweb_timesheet/__pkginfo__.py
cubicweb_timesheet/entities.py
cubicweb_timesheet/hooks.py
cubicweb_timesheet/schema.py
cubicweb_timesheet/data/cubes.timesheet.css
cubicweb_timesheet/data/cubes.timesheet.js
cubicweb_timesheet/i18n/en.po
cubicweb_timesheet/i18n/es.po
cubicweb_timesheet/i18n/fr.po
cubicweb_timesheet/migration/0.12.0_Any.py
cubicweb_timesheet/migration/0.13.0_Any.py
cubicweb_timesheet/migration/0.17.0_Any.py
cubicweb_timesheet/migration/0.18.0_Any.py
cubicweb_timesheet/migration/0.19.0_Any.py
cubicweb_timesheet/migration/0.5.1_Any.py
cubicweb_timesheet/migration/0.9.0_Any.py
cubicweb_timesheet/migration/0.9.1_Any.py
cubicweb_timesheet/migration/1.2.0_Any.py
cubicweb_timesheet/migration/1.4.0_Any.py
cubicweb_timesheet/migration/postcreate.py
cubicweb_timesheet/views/__init__.py
cubicweb_timesheet/views/activity.py
cubicweb_timesheet/views/boxes.py
cubicweb_timesheet/views/commitment.py
cubicweb_timesheet/views/euser.py
cubicweb_timesheet/views/facets.py
cubicweb_timesheet/views/forms.py
cubicweb_timesheet/views/jsonp.py
cubicweb_timesheet/views/primaries.py
cubicweb_timesheet/views/startup.py
cubicweb_timesheet-1.7.0.dist-info/METADATA
cubicweb_timesheet-1.7.0.dist-info/WHEEL
cubicweb_timesheet-1.7.0.dist-info/entry_points.txt
cubicweb_timesheet-1.7.0.dist-info/top_level.txt
cubicweb_timesheet-1.7.0.dist-info/RECORD
