Metadata-Version: 2.4
Name: cubicweb-timesheet
Version: 1.7.0
Summary: record who did what and when for the CubicWeb framework
Home-page: http://www.cubicweb.org/project/cubicweb-timesheet
Author: Logilab
Author-email: contact@logilab.fr
License: LGPL
Classifier: Environment :: Web Environment
Classifier: Framework :: CubicWeb
Classifier: Programming Language :: Python
Classifier: Programming Language :: JavaScript
Requires-Dist: cubicweb<6.0.0,>=4.10.0
Requires-Dist: cubicweb-web<2.0.0,>=1.6.0
Requires-Dist: cubicweb-calendar<2.0.0,>=1.1.0
Requires-Dist: cubicweb-workorder<2.0.0,>=1.1.0
Dynamic: author
Dynamic: author-email
Dynamic: classifier
Dynamic: description
Dynamic: home-page
Dynamic: license
Dynamic: requires-dist
Dynamic: summary
